Compiled from "StudentController.java"
public class com.alex.amigoscodestudent.student.StudentController {
  public com.alex.amigoscodestudent.student.StudentController(com.alex.amigoscodestudent.student.service_implementation.StudentServiceImplementation);
    Code:
       0: aload_0
       1: invokespecial #1                  // Method java/lang/Object."<init>":()V
       4: aload_0
       5: aload_1
       6: putfield      #7                  // Field studentServiceImplementation:Lcom/alex/amigoscodestudent/student/service_implementation/StudentServiceImplementation;
       9: return

  public org.springframework.web.servlet.ModelAndView getStudents(org.springframework.web.servlet.ModelAndView);
    Code:
       0: aload_0
       1: getfield      #7                  // Field studentServiceImplementation:Lcom/alex/amigoscodestudent/student/service_implementation/StudentServiceImplementation;
       4: invokevirtual #13                 // Method com/alex/amigoscodestudent/student/service_implementation/StudentServiceImplementation.getStudents:()Ljava/util/List;
       7: astore_2
       8: aload_1
       9: ldc           #19                 // String students
      11: aload_2
      12: invokevirtual #21                 // Method org/springframework/web/servlet/ModelAndView.addObject:(Ljava/lang/String;Ljava/lang/Object;)Lorg/springframework/web/servlet/ModelAndView;
      15: pop
      16: aload_1
      17: ldc           #27                 // String student/student-list
      19: invokevirtual #29                 // Method org/springframework/web/servlet/ModelAndView.setViewName:(Ljava/lang/String;)V
      22: aload_1
      23: areturn

  public org.springframework.http.ResponseEntity<java.util.Optional<com.alex.amigoscodestudent.student.StudentDto>> getStudentsByRegister(com.alex.amigoscodestudent.student.immutable.Register);
    Code:
       0: aload_0
       1: getfield      #7                  // Field studentServiceImplementation:Lcom/alex/amigoscodestudent/student/service_implementation/StudentServiceImplementation;
       4: aload_1
       5: invokevirtual #33                 // Method com/alex/amigoscodestudent/student/service_implementation/StudentServiceImplementation.getStudentByRegister:(Lcom/alex/amigoscodestudent/student/immutable/Register;)Ljava/util/Optional;
       8: astore_2
       9: aload_2
      10: invokevirtual #37                 // Method java/util/Optional.isPresent:()Z
      13: ifne          27
      16: new           #43                 // class org/springframework/http/ResponseEntity
      19: dup
      20: getstatic     #45                 // Field org/springframework/http/HttpStatus.NOT_FOUND:Lorg/springframework/http/HttpStatus;
      23: invokespecial #51                 // Method org/springframework/http/ResponseEntity."<init>":(Lorg/springframework/http/HttpStatusCode;)V
      26: areturn
      27: new           #43                 // class org/springframework/http/ResponseEntity
      30: dup
      31: aload_2
      32: getstatic     #54                 // Field org/springframework/http/HttpStatus.OK:Lorg/springframework/http/HttpStatus;
      35: invokespecial #57                 // Method org/springframework/http/ResponseEntity."<init>":(Ljava/lang/Object;Lorg/springframework/http/HttpStatusCode;)V
      38: areturn

  public org.springframework.http.ResponseEntity<java.util.Optional<com.alex.amigoscodestudent.student.StudentDto>> getStudentsByName(java.lang.String);
    Code:
       0: aload_0
       1: getfield      #7                  // Field studentServiceImplementation:Lcom/alex/amigoscodestudent/student/service_implementation/StudentServiceImplementation;
       4: aload_1
       5: invokevirtual #60                 // Method com/alex/amigoscodestudent/student/service_implementation/StudentServiceImplementation.getStudentByName:(Ljava/lang/String;)Ljava/util/Optional;
       8: astore_2
       9: aload_2
      10: invokevirtual #37                 // Method java/util/Optional.isPresent:()Z
      13: ifne          27
      16: new           #43                 // class org/springframework/http/ResponseEntity
      19: dup
      20: getstatic     #45                 // Field org/springframework/http/HttpStatus.NOT_FOUND:Lorg/springframework/http/HttpStatus;
      23: invokespecial #51                 // Method org/springframework/http/ResponseEntity."<init>":(Lorg/springframework/http/HttpStatusCode;)V
      26: areturn
      27: new           #43                 // class org/springframework/http/ResponseEntity
      30: dup
      31: aload_2
      32: getstatic     #54                 // Field org/springframework/http/HttpStatus.OK:Lorg/springframework/http/HttpStatus;
      35: invokespecial #57                 // Method org/springframework/http/ResponseEntity."<init>":(Ljava/lang/Object;Lorg/springframework/http/HttpStatusCode;)V
      38: areturn

  public void updateStudent(com.alex.amigoscodestudent.student.immutable.Register, com.alex.amigoscodestudent.student.StudentDto);
    Code:
       0: aload_0
       1: getfield      #7                  // Field studentServiceImplementation:Lcom/alex/amigoscodestudent/student/service_implementation/StudentServiceImplementation;
       4: aload_2
       5: invokevirtual #64                 // Method com/alex/amigoscodestudent/student/service_implementation/StudentServiceImplementation.updateStudent:(Lcom/alex/amigoscodestudent/student/StudentDto;)V
       8: return

  public org.springframework.web.servlet.ModelAndView getStudentByRegisterAndReturnView(java.lang.String);
    Code:
       0: new           #22                 // class org/springframework/web/servlet/ModelAndView
       3: dup
       4: invokespecial #68                 // Method org/springframework/web/servlet/ModelAndView."<init>":()V
       7: astore_2
       8: aload_0
       9: getfield      #7                  // Field studentServiceImplementation:Lcom/alex/amigoscodestudent/student/service_implementation/StudentServiceImplementation;
      12: new           #69                 // class com/alex/amigoscodestudent/student/immutable/Register
      15: dup
      16: aload_1
      17: invokespecial #71                 // Method com/alex/amigoscodestudent/student/immutable/Register."<init>":(Ljava/lang/String;)V
      20: invokevirtual #33                 // Method com/alex/amigoscodestudent/student/service_implementation/StudentServiceImplementation.getStudentByRegister:(Lcom/alex/amigoscodestudent/student/immutable/Register;)Ljava/util/Optional;
      23: astore_3
      24: aload_2
      25: aload_3
      26: invokevirtual #73                 // Method java/util/Optional.get:()Ljava/lang/Object;
      29: checkcast     #77                 // class com/alex/amigoscodestudent/student/StudentDto
      32: invokestatic  #79                 // Method com/alex/amigoscodestudent/student/StudentMapper.mapToStudent:(Lcom/alex/amigoscodestudent/student/StudentDto;)Lcom/alex/amigoscodestudent/student/Student;
      35: invokevirtual #85                 // Method org/springframework/web/servlet/ModelAndView.addObject:(Ljava/lang/Object;)Lorg/springframework/web/servlet/ModelAndView;
      38: pop
      39: aload_2
      40: ldc           #88                 // String student/search/search-result
      42: invokevirtual #29                 // Method org/springframework/web/servlet/ModelAndView.setViewName:(Ljava/lang/String;)V
      45: aload_2
      46: areturn

  public org.springframework.web.servlet.ModelAndView getStudentByNameAndReturnView(java.lang.String);
    Code:
       0: new           #22                 // class org/springframework/web/servlet/ModelAndView
       3: dup
       4: invokespecial #68                 // Method org/springframework/web/servlet/ModelAndView."<init>":()V
       7: astore_2
       8: aload_0
       9: getfield      #7                  // Field studentServiceImplementation:Lcom/alex/amigoscodestudent/student/service_implementation/StudentServiceImplementation;
      12: aload_1
      13: invokevirtual #60                 // Method com/alex/amigoscodestudent/student/service_implementation/StudentServiceImplementation.getStudentByName:(Ljava/lang/String;)Ljava/util/Optional;
      16: astore_3
      17: aload_2
      18: aload_3
      19: invokevirtual #73                 // Method java/util/Optional.get:()Ljava/lang/Object;
      22: checkcast     #77                 // class com/alex/amigoscodestudent/student/StudentDto
      25: invokestatic  #79                 // Method com/alex/amigoscodestudent/student/StudentMapper.mapToStudent:(Lcom/alex/amigoscodestudent/student/StudentDto;)Lcom/alex/amigoscodestudent/student/Student;
      28: invokevirtual #85                 // Method org/springframework/web/servlet/ModelAndView.addObject:(Ljava/lang/Object;)Lorg/springframework/web/servlet/ModelAndView;
      31: pop
      32: aload_2
      33: ldc           #88                 // String student/search/search-result
      35: invokevirtual #29                 // Method org/springframework/web/servlet/ModelAndView.setViewName:(Ljava/lang/String;)V
      38: aload_2
      39: areturn

  public org.springframework.web.servlet.ModelAndView insertNewStudentAndReturnView();
    Code:
       0: new           #22                 // class org/springframework/web/servlet/ModelAndView
       3: dup
       4: invokespecial #68                 // Method org/springframework/web/servlet/ModelAndView."<init>":()V
       7: astore_1
       8: aload_1
       9: new           #90                 // class com/alex/amigoscodestudent/student/Student
      12: dup
      13: invokespecial #92                 // Method com/alex/amigoscodestudent/student/Student."<init>":()V
      16: invokevirtual #85                 // Method org/springframework/web/servlet/ModelAndView.addObject:(Ljava/lang/Object;)Lorg/springframework/web/servlet/ModelAndView;
      19: pop
      20: aload_1
      21: ldc           #93                 // String student/insert/insert
      23: invokevirtual #29                 // Method org/springframework/web/servlet/ModelAndView.setViewName:(Ljava/lang/String;)V
      26: aload_1
      27: areturn

  public org.springframework.web.servlet.ModelAndView updateStudentAndReturnView();
    Code:
       0: new           #22                 // class org/springframework/web/servlet/ModelAndView
       3: dup
       4: invokespecial #68                 // Method org/springframework/web/servlet/ModelAndView."<init>":()V
       7: astore_1
       8: aload_1
       9: new           #90                 // class com/alex/amigoscodestudent/student/Student
      12: dup
      13: invokespecial #92                 // Method com/alex/amigoscodestudent/student/Student."<init>":()V
      16: invokevirtual #85                 // Method org/springframework/web/servlet/ModelAndView.addObject:(Ljava/lang/Object;)Lorg/springframework/web/servlet/ModelAndView;
      19: pop
      20: aload_1
      21: ldc           #95                 // String student/update/update
      23: invokevirtual #29                 // Method org/springframework/web/servlet/ModelAndView.setViewName:(Ljava/lang/String;)V
      26: aload_1
      27: areturn

  public org.springframework.web.servlet.ModelAndView insertNewStudentAndSubmit(com.alex.amigoscodestudent.student.StudentDto);
    Code:
       0: aload_0
       1: getfield      #7                  // Field studentServiceImplementation:Lcom/alex/amigoscodestudent/student/service_implementation/StudentServiceImplementation;
       4: aload_1
       5: invokevirtual #97                 // Method com/alex/amigoscodestudent/student/service_implementation/StudentServiceImplementation.addNewStudent:(Lcom/alex/amigoscodestudent/student/StudentDto;)V
       8: new           #22                 // class org/springframework/web/servlet/ModelAndView
      11: dup
      12: invokespecial #68                 // Method org/springframework/web/servlet/ModelAndView."<init>":()V
      15: astore_2
      16: aload_2
      17: aload_1
      18: invokestatic  #79                 // Method com/alex/amigoscodestudent/student/StudentMapper.mapToStudent:(Lcom/alex/amigoscodestudent/student/StudentDto;)Lcom/alex/amigoscodestudent/student/Student;
      21: invokevirtual #85                 // Method org/springframework/web/servlet/ModelAndView.addObject:(Ljava/lang/Object;)Lorg/springframework/web/servlet/ModelAndView;
      24: pop
      25: aload_2
      26: ldc           #100                // String student/insert/insert-result
      28: invokevirtual #29                 // Method org/springframework/web/servlet/ModelAndView.setViewName:(Ljava/lang/String;)V
      31: aload_2
      32: areturn

  public org.springframework.web.servlet.ModelAndView updateStudentAndReturnView(com.alex.amigoscodestudent.student.StudentDto);
    Code:
       0: aload_0
       1: getfield      #7                  // Field studentServiceImplementation:Lcom/alex/amigoscodestudent/student/service_implementation/StudentServiceImplementation;
       4: aload_1
       5: invokevirtual #64                 // Method com/alex/amigoscodestudent/student/service_implementation/StudentServiceImplementation.updateStudent:(Lcom/alex/amigoscodestudent/student/StudentDto;)V
       8: new           #22                 // class org/springframework/web/servlet/ModelAndView
      11: dup
      12: invokespecial #68                 // Method org/springframework/web/servlet/ModelAndView."<init>":()V
      15: astore_2
      16: aload_2
      17: aload_1
      18: invokestatic  #79                 // Method com/alex/amigoscodestudent/student/StudentMapper.mapToStudent:(Lcom/alex/amigoscodestudent/student/StudentDto;)Lcom/alex/amigoscodestudent/student/Student;
      21: invokevirtual #85                 // Method org/springframework/web/servlet/ModelAndView.addObject:(Ljava/lang/Object;)Lorg/springframework/web/servlet/ModelAndView;
      24: pop
      25: aload_2
      26: ldc           #102                // String student/update/update-result
      28: invokevirtual #29                 // Method org/springframework/web/servlet/ModelAndView.setViewName:(Ljava/lang/String;)V
      31: aload_2
      32: areturn

  public org.springframework.web.servlet.ModelAndView deleteStudentByIdAndReturnView(com.alex.amigoscodestudent.student.immutable.Register);
    Code:
       0: new           #22                 // class org/springframework/web/servlet/ModelAndView
       3: dup
       4: invokespecial #68                 // Method org/springframework/web/servlet/ModelAndView."<init>":()V
       7: astore_2
       8: aload_0
       9: getfield      #7                  // Field studentServiceImplementation:Lcom/alex/amigoscodestudent/student/service_implementation/StudentServiceImplementation;
      12: aload_1
      13: invokevirtual #104                // Method com/alex/amigoscodestudent/student/service_implementation/StudentServiceImplementation.deleteStudent:(Lcom/alex/amigoscodestudent/student/immutable/Register;)V
      16: aload_2
      17: ldc           #108                // String student/delete/delete-result
      19: invokevirtual #29                 // Method org/springframework/web/servlet/ModelAndView.setViewName:(Ljava/lang/String;)V
      22: aload_2
      23: areturn

  public org.springframework.web.servlet.ModelAndView deleteStudentByNameAndReturnView(java.lang.String);
    Code:
       0: new           #22                 // class org/springframework/web/servlet/ModelAndView
       3: dup
       4: invokespecial #68                 // Method org/springframework/web/servlet/ModelAndView."<init>":()V
       7: astore_2
       8: aload_0
       9: getfield      #7                  // Field studentServiceImplementation:Lcom/alex/amigoscodestudent/student/service_implementation/StudentServiceImplementation;
      12: aload_1
      13: invokevirtual #60                 // Method com/alex/amigoscodestudent/student/service_implementation/StudentServiceImplementation.getStudentByName:(Ljava/lang/String;)Ljava/util/Optional;
      16: astore_3
      17: aload_0
      18: getfield      #7                  // Field studentServiceImplementation:Lcom/alex/amigoscodestudent/student/service_implementation/StudentServiceImplementation;
      21: aload_1
      22: invokevirtual #60                 // Method com/alex/amigoscodestudent/student/service_implementation/StudentServiceImplementation.getStudentByName:(Ljava/lang/String;)Ljava/util/Optional;
      25: invokevirtual #73                 // Method java/util/Optional.get:()Ljava/lang/Object;
      28: checkcast     #77                 // class com/alex/amigoscodestudent/student/StudentDto
      31: invokevirtual #110                // Method com/alex/amigoscodestudent/student/StudentDto.getRegister:()Lcom/alex/amigoscodestudent/student/immutable/Register;
      34: astore        4
      36: aload_0
      37: getfield      #7                  // Field studentServiceImplementation:Lcom/alex/amigoscodestudent/student/service_implementation/StudentServiceImplementation;
      40: aload         4
      42: invokevirtual #104                // Method com/alex/amigoscodestudent/student/service_implementation/StudentServiceImplementation.deleteStudent:(Lcom/alex/amigoscodestudent/student/immutable/Register;)V
      45: aload_2
      46: aload_3
      47: invokevirtual #73                 // Method java/util/Optional.get:()Ljava/lang/Object;
      50: invokevirtual #85                 // Method org/springframework/web/servlet/ModelAndView.addObject:(Ljava/lang/Object;)Lorg/springframework/web/servlet/ModelAndView;
      53: pop
      54: aload_2
      55: ldc           #108                // String student/delete/delete-result
      57: invokevirtual #29                 // Method org/springframework/web/servlet/ModelAndView.setViewName:(Ljava/lang/String;)V
      60: aload_2
      61: areturn
}
